{"features": [{"geometry": {"coordinates": [32.31206, 52.29781], "type": "Point"}, "properties": {"adminCode1": "10", "adminName1": "Brjansk", "countryCode": "RU", "countryId": "2017370", "countryName": "Russia", "east": 34.5481, "fcl": "P", "fclName": "city, village,...", "fcode": "PPL", "fcodeName": "populated place", "featureClass": "P", "fuzzy": 1, "geonameId": 516874, "hgr_id": 585, "lat": "52.29781", "lng": "32.31206", "name": "\u0420\u043e\u043f\u0441\u043a", "north": 53.3902, "population": 1293, "south": 50.7177, "toponymName": "Novyy Ropsk", "type": "json", "url": "http://api.geonames.org/search?north=53.3902&east=34.5481&type=json&west=31.3047&fuzzy=1&username=jaguillette&name=%D0%A0%D0%BE%D0%BF%D1%81%D0%BA&featureClass=P&south=50.7177", "username": "jaguillette", "west": 31.3047}, "type": "Feature"}, {"geometry": {"coordinates": [32.25882, 52.30876], "type": "Point"}, "properties": {"adminCode1": "10", "adminName1": "Brjansk", "countryCode": "RU", "countryId": "2017370", "countryName": "Russia", "east": 34.5481, "fcl": "P", "fclName": "city, village,...", "fcode": "PPL", "fcodeName": "populated place", "featureClass": "P", "fuzzy": 1, "geonameId": 487912, "hgr_id": 585, "lat": "52.30876", "lng": "32.25882", "name": "\u0420\u043e\u043f\u0441\u043a", "north": 53.3902, "population": 202, "south": 50.7177, "toponymName": "Staryy Ropsk", "type": "json", "url": "http://api.geonames.org/search?north=53.3902&east=34.5481&type=json&west=31.3047&fuzzy=1&username=jaguillette&name=%D0%A0%D0%BE%D0%BF%D1%81%D0%BA&featureClass=P&south=50.7177", "username": "jaguillette", "west": 31.3047}, "type": "Feature"}], "type": "FeatureCollection"}