{"geonames": [{"adminCode1": "85", "adminName1": "Vologda", "countryCode": "RU", "countryId": "2017370", "countryName": "Russia", "fcl": "P", "fclName": "city, village,...", "fcode": "PPL", "fcodeName": "populated place", "geonameId": 497505, "lat": "60.3272", "lng": "37.4306", "name": "Semenchevo", "population": 0, "toponymName": "Semenchevo"}, {"adminCode1": "77", "adminName1": "Tverskaya", "countryCode": "RU", "countryId": "2017370", "countryName": "Russia", "fcl": "P", "fclName": "city, village,...", "fcode": "PPL", "fcodeName": "populated place", "geonameId": 497500, "lat": "57.30389", "lng": "38.22556", "name": "Semendyayevo", "population": 0, "toponymName": "Semendyayevo"}, {"adminCode1": "69", "adminName1": "Smolensk", "countryCode": "RU", "countryId": "2017370", "countryName": "Russia", "fcl": "P", "fclName": "city, village,...", "fcode": "PPL", "fcodeName": "populated place", "geonameId": 497269, "lat": "55.7228", "lng": "34.43135", "name": "Sements\u00ebvo", "population": 0, "toponymName": "Sements\u00ebvo"}, {"adminCode1": "69", "adminName1": "Smolensk", "countryCode": "RU", "countryId": "2017370", "countryName": "Russia", "fcl": "P", "fclName": "city, village,...", "fcode": "PPL", "fcodeName": "populated place", "geonameId": 497501, "lat": "54.94721", "lng": "33.06861", "name": "Semendyayevo", "population": 0, "toponymName": "Semendyayevo"}, {"adminCode1": "56", "adminName1": "Orjol", "countryCode": "RU", "countryId": "2017370", "countryName": "Russia", "fcl": "P", "fclName": "city, village,...", "fcode": "PPL", "fcodeName": "populated place", "geonameId": 7451568, "lat": "52.8651", "lng": "36.3013", "name": "Semendyayevo", "population": 0, "toponymName": "Semendyayevo"}, {"adminCode1": "88", "adminName1": "Jaroslavl", "countryCode": "RU", "countryId": "2017370", "countryName": "Russia", "fcl": "P", "fclName": "city, village,...", "fcode": "PPL", "fcodeName": "populated place", "geonameId": 497267, "lat": "57.86944", "lng": "38.19334", "name": "Sements\u00ebvo", "population": 0, "toponymName": "Sements\u00ebvo"}, {"adminCode1": "88", "adminName1": "Jaroslavl", "countryCode": "RU", "countryId": "2017370", "countryName": "Russia", "fcl": "P", "fclName": "city, village,...", "fcode": "PPL", "fcodeName": "populated place", "geonameId": 497268, "lat": "57.5", "lng": "38.05", "name": "Sements\u00ebvo", "population": 0, "toponymName": "Sements\u00ebvo"}, {"adminCode1": "77", "adminName1": "Tverskaya", "countryCode": "RU", "countryId": "2017370", "countryName": "Russia", "fcl": "P", "fclName": "city, village,...", "fcode": "PPL", "fcodeName": "populated place", "geonameId": 7586720, "lat": "57.07", "lng": "37.0787", "name": "Sements\u00ebvo", "population": 0, "toponymName": "Sements\u00ebvo"}, {"adminCode1": "77", "adminName1": "Tverskaya", "countryCode": "RU", "countryId": "2017370", "countryName": "Russia", "fcl": "P", "fclName": "city, village,...", "fcode": "PPL", "fcodeName": "populated place", "geonameId": 822463, "lat": "56.52972", "lng": "33.27028", "name": "Sementsevo", "population": 0, "toponymName": "Sementsevo"}], "searchinfo": {"east": 39.921928, "featureClass": "P", "fuzzy": 0.7000000000000001, "hgr_id": 616, "name": "\u0421\u0435\u043c\u0435\u043d\u0434\u0435\u0435\u0432\u043e", "north": 60.857828, "south": 52.857828, "type": "json", "url": "http://api.geonames.org/search?name=%D0%A1%D0%B5%D0%BC%D0%B5%D0%BD%D0%B4%D0%B5%D0%B5%D0%B2%D0%BE&type=json&north=60.857828&featureClass=P&east=39.921928&west=31.921928&south=52.857828&username=jaguillette&fuzzy=0.7000000000000001", "username": "jaguillette", "west": 31.921928}, "totalResultsCount": 9}