{"geonames": [{"adminCode1": "48", "adminName1": "Moscow", "countryCode": "RU", "countryId": "2017370", "countryName": "Russia", "fcl": "P", "fclName": "city, village,...", "fcode": "PPLX", "fcodeName": "section of populated place", "geonameId": 6418220, "lat": "55.61252", "lng": "37.72639", "name": "Orekhovo-Borisovo", "population": 144000, "toponymName": "Orekhovo-Borisovo"}, {"adminCode1": "47", "adminName1": "Moskovskaya", "countryCode": "RU", "countryId": "2017370", "countryName": "Russia", "fcl": "P", "fclName": "city, village,...", "fcode": "PPL", "fcodeName": "populated place", "geonameId": 572451, "lat": "55.41972", "lng": "36.04611", "name": "Borisovo", "population": 0, "toponymName": "Borisovo"}, {"adminCode1": "48", "adminName1": "Moscow", "countryCode": "RU", "countryId": "2017370", "countryName": "Russia", "fcl": "P", "fclName": "city, village,...", "fcode": "PPLX", "fcodeName": "section of populated place", "geonameId": 515027, "lat": "55.61667", "lng": "37.68333", "name": "Orekhovo-Borisovo Severnoye", "population": 128000, "toponymName": "Orekhovo-Borisovo Severnoye"}, {"adminCode1": "47", "adminName1": "Moskovskaya", "countryCode": "RU", "countryId": "2017370", "countryName": "Russia", "fcl": "P", "fclName": "city, village,...", "fcode": "PPL", "fcodeName": "populated place", "geonameId": 572444, "lat": "56.33333", "lng": "36.65", "name": "Borisovo", "population": 0, "toponymName": "Borisovo"}, {"adminCode1": "47", "adminName1": "Moskovskaya", "countryCode": "RU", "countryId": "2017370", "countryName": "Russia", "fcl": "P", "fclName": "city, village,...", "fcode": "PPL", "fcodeName": "populated place", "geonameId": 572447, "lat": "55.8", "lng": "39.71667", "name": "Borisovo", "population": 0, "toponymName": "Borisovo"}, {"adminCode1": "47", "adminName1": "Moskovskaya", "countryCode": "RU", "countryId": "2017370", "countryName": "Russia", "fcl": "P", "fclName": "city, village,...", "fcode": "PPL", "fcodeName": "populated place", "geonameId": 572455, "lat": "55.19495", "lng": "38.48885", "name": "Borisovo", "population": 0, "toponymName": "Borisovo"}, {"adminCode1": "25", "adminName1": "Kaluga", "countryCode": "RU", "countryId": "2017370", "countryName": "Russia", "fcl": "P", "fclName": "city, village,...", "fcode": "PPL", "fcodeName": "populated place", "geonameId": 572456, "lat": "55.17472", "lng": "36.08083", "name": "Borisovo", "population": 0, "toponymName": "Borisovo"}, {"adminCode1": "62", "adminName1": "Rjazan", "countryCode": "RU", "countryId": "2017370", "countryName": "Russia", "fcl": "P", "fclName": "city, village,...", "fcode": "PPL", "fcodeName": "populated place", "geonameId": 572459, "lat": "55.08028", "lng": "40.21129", "name": "Borisovo", "population": 0, "toponymName": "Borisovo"}, {"adminCode1": "76", "adminName1": "Tula", "countryCode": "RU", "countryId": "2017370", "countryName": "Russia", "fcl": "P", "fclName": "city, village,...", "fcode": "PPL", "fcodeName": "populated place", "geonameId": 572462, "lat": "54.61667", "lng": "38.13333", "name": "Borisovo", "population": 0, "toponymName": "Borisovo"}, {"adminCode1": "76", "adminName1": "Tula", "countryCode": "RU", "countryId": "2017370", "countryName": "Russia", "fcl": "P", "fclName": "city, village,...", "fcode": "PPL", "fcodeName": "populated place", "geonameId": 572463, "lat": "54.39744", "lng": "37.12199", "name": "Borisovo", "population": 0, "toponymName": "Borisovo"}, {"adminCode1": "25", "adminName1": "Kaluga", "countryCode": "RU", "countryId": "2017370", "countryName": "Russia", "fcl": "P", "fclName": "city, village,...", "fcode": "PPL", "fcodeName": "populated place", "geonameId": 817319, "lat": "54.39833", "lng": "35.0125", "name": "Borisovo", "population": 0, "toponymName": "Borisovo"}, {"adminCode1": "77", "adminName1": "Tverskaya", "countryCode": "RU", "countryId": "2017370", "countryName": "Russia", "fcl": "P", "fclName": "city, village,...", "fcode": "PPL", "fcodeName": "populated place", "geonameId": 7600965, "lat": "56.9671", "lng": "36.0942", "name": "Borisovo", "population": 0, "toponymName": "Borisovo"}, {"adminCode1": "47", "adminName1": "Moskovskaya", "countryCode": "RU", "countryId": "2017370", "countryName": "Russia", "fcl": "P", "fclName": "city, village,...", "fcode": "PPL", "fcodeName": "populated place", "geonameId": 572453, "lat": "55.3579", "lng": "38.04945", "name": "Borisovo", "population": 0, "toponymName": "Borisovo"}, {"adminCode1": "25", "adminName1": "Kaluga", "countryCode": "RU", "countryId": "2017370", "countryName": "Russia", "fcl": "P", "fclName": "city, village,...", "fcode": "PPL", "fcodeName": "populated place", "geonameId": 572457, "lat": "55.15183", "lng": "36.94383", "name": "Borisovo", "population": 0, "toponymName": "Borisovo"}, {"adminCode1": "88", "adminName1": "Jaroslavl", "countryCode": "RU", "countryId": "2017370", "countryName": "Russia", "fcl": "P", "fclName": "city, village,...", "fcode": "PPL", "fcodeName": "populated place", "geonameId": 572439, "lat": "56.65601", "lng": "38.78748", "name": "Borisovo", "population": 0, "toponymName": "Borisovo"}, {"adminCode1": "76", "adminName1": "Tula", "countryCode": "RU", "countryId": "2017370", "countryName": "Russia", "fcl": "P", "fclName": "city, village,...", "fcode": "PPL", "fcodeName": "populated place", "geonameId": 572461, "lat": "54.75215", "lng": "37.81275", "name": "Borisovo", "population": 0, "toponymName": "Borisovo"}, {"adminCode1": "47", "adminName1": "Moskovskaya", "countryCode": "RU", "countryId": "2017370", "countryName": "Russia", "fcl": "P", "fclName": "city, village,...", "fcode": "PPL", "fcodeName": "populated place", "geonameId": 572460, "lat": "54.92094", "lng": "37.48255", "name": "Borisovo", "population": 0, "toponymName": "Borisovo"}, {"adminCode1": "83", "adminName1": "Vladimir", "countryCode": "RU", "countryId": "2017370", "countryName": "Russia", "fcl": "P", "fclName": "city, village,...", "fcode": "PPL", "fcodeName": "populated place", "geonameId": 7077470, "lat": "56.19561", "lng": "39.83416", "name": "Borisovo", "population": 0, "toponymName": "Borisovo"}, {"adminCode1": "88", "adminName1": "Jaroslavl", "countryCode": "RU", "countryId": "2017370", "countryName": "Russia", "fcl": "P", "fclName": "city, village,...", "fcode": "PPL", "fcodeName": "populated place", "geonameId": 7077690, "lat": "56.6716", "lng": "39.19882", "name": "Borisovo", "population": 0, "toponymName": "Borisovo"}, {"adminCode1": "47", "adminName1": "Moskovskaya", "countryCode": "RU", "countryId": "2017370", "countryName": "Russia", "fcl": "P", "fclName": "city, village,...", "fcode": "PPL", "fcodeName": "populated place", "geonameId": 572411, "lat": "54.78884", "lng": "38.96063", "name": "Borisovo-Okolitsy", "population": 0, "toponymName": "Borisovo-Okolitsy"}, {"adminCode1": "48", "adminName1": "Moscow", "countryCode": "RU", "countryId": "2017370", "countryName": "Russia", "fcl": "P", "fclName": "city, village,...", "fcode": "PPLX", "fcodeName": "section of populated place", "geonameId": 572449, "lat": "55.63333", "lng": "37.73333", "name": "Orekhovo-Borisovo Yuzhnoye", "population": 0, "toponymName": "Orekhovo-Borisovo Yuzhnoye"}, {"adminCode1": "47", "adminName1": "Moskovskaya", "countryCode": "RU", "countryId": "2017370", "countryName": "Russia", "fcl": "P", "fclName": "city, village,...", "fcode": "PPL", "fcodeName": "populated place", "geonameId": 816033, "lat": "55.24389", "lng": "36.16639", "name": "Novo-Borisovo", "population": 0, "toponymName": "Novo-Borisovo"}, {"adminCode1": "25", "adminName1": "Kaluga", "countryCode": "RU", "countryId": "2017370", "countryName": "Russia", "fcl": "P", "fclName": "city, village,...", "fcode": "PPL", "fcodeName": "populated place", "geonameId": 555059, "lat": "54.61532", "lng": "36.698", "name": "Ivash\u00ebvo", "population": 0, "toponymName": "Ivash\u00ebvo"}, {"adminCode1": "47", "adminName1": "Moskovskaya", "countryCode": "RU", "countryId": "2017370", "countryName": "Russia", "fcl": "P", "fclName": "city, village,...", "fcode": "PPL", "fcodeName": "populated place", "geonameId": 572458, "lat": "55.1301", "lng": "38.58146", "name": "Borisovskoye", "population": 0, "toponymName": "Borisovskoye"}], "searchinfo": {"east": 40.3419, "featureClass": "P", "fuzzy": 1, "hgr_id": 63, "name": "\u0411\u043e\u0440\u0438\u0441\u043e\u0432\u043e", "north": 56.981, "south": 54.2132, "type": "json", "url": "http://api.geonames.org/search?name=%D0%91%D0%BE%D1%80%D0%B8%D1%81%D0%BE%D0%B2%D0%BE&type=json&north=56.981&featureClass=P&east=40.3419&west=34.3446&south=54.2132&username=jaguillette&fuzzy=1", "username": "jaguillette", "west": 34.3446}, "totalResultsCount": 24}