{"totalResultsCount":10,"geonames":[{"countryId":"2017370","adminCode1":"47","countryName":"Russia","fclName":"city, village,...","countryCode":"RU","lng":"36.4","fcodeName":"populated place","toponymName":"Arkhangel’sk","fcl":"P","name":"Arkhangel'sk","fcode":"PPL","geonameId":581050,"lat":"55.48333","adminName1":"Moskovskaya","population":0},{"countryId":"2017370","adminCode1":"47","countryName":"Russia","fclName":"city, village,...","countryCode":"RU","lng":"36.4","fcodeName":"populated place","toponymName":"Novo-Arkhangel’sk","fcl":"P","name":"Novo-Arkhangel’sk","fcode":"PPL","geonameId":519058,"lat":"55.45","adminName1":"Moskovskaya","population":0},{"countryId":"2017370","adminCode1":"10","countryName":"Russia","fclName":"city, village,...","countryCode":"RU","lng":"34.01667","fcodeName":"populated place","toponymName":"Novo-Arkhangel’sk","fcl":"P","name":"Novo-Arkhangel’sk","fcode":"PPL","geonameId":519059,"lat":"53.21667","adminName1":"Brjansk","population":0},{"countryId":"2017370","adminCode1":"83","countryName":"Russia","fclName":"city, village,...","countryCode":"RU","lng":"41.54806","fcodeName":"populated place","toponymName":"Arkhangel","fcl":"P","name":"Arkhangel","fcode":"PPL","geonameId":581058,"lat":"55.45","adminName1":"Vladimir","population":0},{"countryId":"690791","adminCode1":"07","countryName":"Ukraine","fclName":"city, village,...","countryCode":"UA","lng":"36.93694","fcodeName":"populated place","toponymName":"Arkhanhelivka","fcl":"P","name":"Arkhanhelivka","fcode":"PPL","geonameId":713210,"lat":"48.93667","adminName1":"Kharkiv","population":0},{"countryId":"2017370","adminCode1":"55","countryName":"Russia","fclName":"city, village,...","countryCode":"RU","lng":"59.2624","fcodeName":"populated place","toponymName":"Arkhangel’skoye","fcl":"P","name":"Arkhangel'skoye","fcode":"PPL","geonameId":581025,"lat":"50.7908","adminName1":"Orenburg","population":0},{"countryId":"2017370","adminCode1":"93","countryName":"Russia","fclName":"city, village,...","countryCode":"RU","lng":"108.74933","fcodeName":"populated place","toponymName":"Arkhangel’skoye","fcl":"P","name":"Arkhangel'skoye","fcode":"PPL","geonameId":2027488,"lat":"50.31753","adminName1":"Zabaykalsky","population":0},{"countryId":"2017370","adminCode1":"13","countryName":"Russia","fclName":"city, village,...","countryCode":"RU","lng":"59.7438","fcodeName":"populated place","toponymName":"Arkhangel’skoye","fcl":"P","name":"Arkhangel'skoye","fcode":"PPL","geonameId":580998,"lat":"54.9027","adminName1":"Chelyabinsk","population":0},{"countryId":"2017370","adminCode1":"43","countryName":"Russia","fclName":"city, village,...","countryCode":"RU","lng":"38.61196","fcodeName":"populated place","toponymName":"Arkhangel’skoye","fcl":"P","name":"Arkhangel'sk","fcode":"PPL","geonameId":581051,"lat":"52.56647","adminName1":"Lipetsk","population":0},{"countryId":"2017370","adminCode1":"47","countryName":"Russia","fclName":"city, village,...","countryCode":"RU","lng":"35.9625","fcodeName":"populated place","toponymName":"Arkhangel’skoye","fcl":"P","name":"Arkhangel’skoye","fcode":"PPL","geonameId":580995,"lat":"55.32194","adminName1":"Moskovskaya","population":0}]}