{"geonames": [{"fcl": "P", "countryName": "Ukraine", "adminCode1": "21", "fcodeName": "populated place", "adminName1": "Sumy", "lng": "33.45944", "name": "Voronezh", "toponymName": "Voronizh", "lat": "51.77572", "fclName": "city, village,...", "geonameId": 689025, "fcode": "PPL", "population": 0, "countryCode": "UA", "countryId": "690791"}], "totalResultsCount": 1, "url": "http://api.geonames.org/search?north=55.5&west=27.3&south=47.5&name=%D0%92%D0%BE%D1%80%D0%BE%D0%BD%D0%B5%D0%B6&username=jaguillette&east=35.3&featureClass=P&type=json"}