{"geonames": [{"fcl": "P", "countryName": "Russia", "adminCode1": "56", "fcodeName": "populated place", "adminName1": "Orjol", "lng": "37.65833", "name": "Luna-Gavrilova", "toponymName": "Luna-Gavrilova", "lat": "52.89111", "fclName": "city, village,...", "geonameId": 533318, "fcode": "PPL", "population": 0, "countryCode": "RU", "countryId": "2017370"}, {"fcl": "P", "countryName": "Russia", "adminCode1": "47", "fcodeName": "populated place", "adminName1": "Moskovskaya", "lng": "38.58917", "name": "Gavrilovo", "toponymName": "Gavrilovo", "lat": "55.94667", "fclName": "city, village,...", "geonameId": 561837, "fcode": "PPL", "population": 0, "countryCode": "RU", "countryId": "2017370"}], "totalResultsCount": 2, "url": "http://api.geonames.org/search?north=60.133333&west=36.416667&south=52.133333&name=%D0%93%D0%B0%D0%B2%D1%80%D0%B8%D0%BB%D0%BE%D0%B2%D0%B0&username=jaguillette&east=44.416667&featureClass=P&type=json"}