{"geonames": [{"fcl": "P", "countryName": "Russia", "adminCode1": "10", "fcodeName": "populated place", "adminName1": "Brjansk", "lng": "33.10627", "name": "Kist\u00ebr", "toponymName": "Kist\u00ebr", "lat": "52.40773", "fclName": "city, village,...", "geonameId": 548076, "fcode": "PPL", "population": 0, "countryCode": "RU", "countryId": "2017370"}], "totalResultsCount": 1, "url": "http://api.geonames.org/search?north=55.983333&west=29.266666999999998&south=47.983333&name=%D0%9A%D0%B8%D1%81%D1%82%D0%B5%D1%80&username=jaguillette&east=37.266667&featureClass=P&type=json"}