{"geonames": [{"fcl": "P", "countryName": "Ukraine", "adminCode1": "04", "fcodeName": "populated place", "adminName1": "Dnipropetrovsk", "lng": "33.94792", "name": "Myshuryn Rih", "toponymName": "Myshuryn Rih", "lat": "48.81817", "fclName": "city, village,...", "geonameId": 701000, "fcode": "PPL", "population": 0, "countryCode": "UA", "countryId": "690791"}], "totalResultsCount": 1, "url": "http://api.geonames.org/search?north=49.99&west=29.6&south=46.07&name=%D0%9C%D0%B8%D1%88%D1%83%D1%80%D0%B8%D0%BD+%D0%A0%D0%BE%D0%B3&username=jaguillette&east=39.14&featureClass=P&type=json"}