{"geonames": [{"fcl": "P", "countryName": "Russia", "adminCode1": "56", "fcodeName": "populated place", "adminName1": "Orjol", "lng": "37.04048", "name": "Novosil'", "toponymName": "Novosil\u2019", "lat": "52.97387", "fclName": "city, village,...", "geonameId": 517947, "fcode": "PPL", "population": 3989, "countryCode": "RU", "countryId": "2017370"}], "totalResultsCount": 1, "url": "http://api.geonames.org/search?north=55.0867&west=35.5421&south=52.8329&name=%D0%9D%D0%BE%D0%B2%D0%BE%D1%81%D0%B8%D0%BB%D1%8C&username=jaguillette&east=39.6827&featureClass=P&type=json"}