{"geonames": [{"fcl": "P", "countryName": "Russia", "adminCode1": "55", "fcodeName": "populated place", "adminName1": "Orenburg", "lng": "58.3917", "name": "Pisarevka", "toponymName": "Pisarevka", "lat": "51.5978", "fclName": "city, village,...", "geonameId": 509344, "fcode": "PPL", "population": 0, "countryCode": "RU", "countryId": "2017370"}, {"fcl": "P", "countryName": "Russia", "adminCode1": "86", "fcodeName": "populated place", "adminName1": "Voronezj", "lng": "40.18519", "name": "Pisarevka", "toponymName": "Pisarevka", "lat": "49.88545", "fclName": "city, village,...", "geonameId": 509359, "fcode": "PPL", "population": 0, "countryCode": "RU", "countryId": "2017370"}, {"fcl": "P", "countryName": "Russia", "adminCode1": "10", "fcodeName": "populated place", "adminName1": "Brjansk", "lng": "32.71259", "name": "Pisarevka", "toponymName": "Pisarevka", "lat": "52.92598", "fclName": "city, village,...", "geonameId": 509352, "fcode": "PPL", "population": 0, "countryCode": "RU", "countryId": "2017370"}, {"fcl": "P", "countryName": "Russia", "adminCode1": "84", "fcodeName": "populated place", "adminName1": "Volgograd", "lng": "43.98568", "name": "Pisarevka", "toponymName": "Pisarevka", "lat": "49.6738", "fclName": "city, village,...", "geonameId": 509360, "fcode": "PPL", "population": 0, "countryCode": "RU", "countryId": "2017370"}, {"fcl": "P", "countryName": "Russia", "adminCode1": "72", "fcodeName": "populated place", "adminName1": "Tambov", "lng": "40.7826", "name": "Pisarevka", "toponymName": "Pisarevka", "lat": "52.24", "fclName": "city, village,...", "geonameId": 509357, "fcode": "PPL", "population": 0, "countryCode": "RU", "countryId": "2017370"}, {"fcl": "P", "countryName": "Russia", "adminCode1": "86", "fcodeName": "populated place", "adminName1": "Voronezj", "lng": "39.3487", "name": "Pisarevka", "toponymName": "Pisarevka", "lat": "52.06496", "fclName": "city, village,...", "geonameId": 509358, "fcode": "PPL", "population": 0, "countryCode": "RU", "countryId": "2017370"}, {"fcl": "P", "countryName": "Russia", "adminCode1": "43", "fcodeName": "populated place", "adminName1": "Lipetsk", "lng": "39.36071", "name": "Pisarevka", "toponymName": "Pisarevka", "lat": "52.91852", "fclName": "city, village,...", "geonameId": 509353, "fcode": "PPL", "population": 0, "countryCode": "RU", "countryId": "2017370"}, {"fcl": "P", "countryName": "Russia", "adminCode1": "84", "fcodeName": "populated place", "adminName1": "Volgograd", "lng": "43.9856", "name": "Pisarevka", "toponymName": "Pisarevka", "lat": "49.6751", "fclName": "city, village,...", "geonameId": 509361, "fcode": "PPL", "population": 0, "countryCode": "RU", "countryId": "2017370"}, {"fcl": "P", "countryName": "Russia", "adminCode1": "84", "fcodeName": "populated place", "adminName1": "Volgograd", "lng": "44.18743", "name": "Pisarevka", "toponymName": "Pisarevka", "lat": "49.48026", "fclName": "city, village,...", "geonameId": 509362, "fcode": "PPL", "population": 0, "countryCode": "RU", "countryId": "2017370"}, {"fcl": "P", "countryName": "Russia", "adminCode1": "43", "fcodeName": "populated place", "adminName1": "Lipetsk", "lng": "39.7122", "name": "Pisarevka", "toponymName": "Pisarevka", "lat": "52.40611", "fclName": "city, village,...", "geonameId": 509356, "fcode": "PPL", "population": 0, "countryCode": "RU", "countryId": "2017370"}, {"fcl": "P", "countryName": "Russia", "adminCode1": "53", "fcodeName": "populated place", "adminName1": "Novosibirsk", "lng": "78.41667", "name": "Pisarevka", "toponymName": "Pisarevka", "lat": "53.53333", "fclName": "city, village,...", "geonameId": 1494938, "fcode": "PPL", "population": 0, "countryCode": "RU", "countryId": "2017370"}, {"fcl": "P", "countryName": "Kazakhstan", "adminCode1": "00", "fcodeName": "populated place", "adminName1": "", "lng": "70.73498", "name": "Pisarevka", "toponymName": "Pisarevka", "lat": "54.63212", "fclName": "city, village,...", "geonameId": 1520143, "fcode": "PPL", "population": 0, "countryCode": "KZ", "countryId": "1522867"}, {"fcl": "P", "countryName": "Ukraine", "adminCode1": "18", "fcodeName": "populated place", "adminName1": "Poltava", "lng": "34.61297", "name": "Pisarevka", "toponymName": "Pisarevka", "lat": "49.42356", "fclName": "city, village,...", "geonameId": 697172, "fcode": "PPL", "population": 0, "countryCode": "UA", "countryId": "690791"}, {"fcl": "P", "countryName": "Russia", "adminCode1": "43", "fcodeName": "populated place", "adminName1": "Lipetsk", "lng": "38.80043", "name": "Pisarevka", "toponymName": "Pisarevka", "lat": "52.22714", "fclName": "city, village,...", "geonameId": 509349, "fcode": "PPL", "population": 0, "countryCode": "RU", "countryId": "2017370"}, {"fcl": "P", "countryName": "Russia", "adminCode1": "61", "fcodeName": "populated place", "adminName1": "Rostov", "lng": "38.78722", "name": "Pisarevka", "toponymName": "Pisarevka", "lat": "47.71861", "fclName": "city, village,...", "geonameId": 509363, "fcode": "PPL", "population": 0, "countryCode": "RU", "countryId": "2017370"}, {"fcl": "P", "countryName": "Russia", "adminCode1": "62", "fcodeName": "populated place", "adminName1": "Rjazan", "lng": "39.0857", "name": "Pisarevka", "toponymName": "Pisarevka", "lat": "53.7951", "fclName": "city, village,...", "geonameId": 7450306, "fcode": "PPL", "population": 0, "countryCode": "RU", "countryId": "2017370"}, {"fcl": "P", "countryName": "Russia", "adminCode1": "09", "fcodeName": "populated place", "adminName1": "Belgorod", "lng": "37.1347", "name": "Pisarevka", "toponymName": "Pisarevka", "lat": "51.1121", "fclName": "city, village,...", "geonameId": 806157, "fcode": "PPL", "population": 0, "countryCode": "RU", "countryId": "2017370"}, {"fcl": "P", "countryName": "Belarus", "adminCode1": "06", "fcodeName": "populated place", "adminName1": "Mogilev", "lng": "29.9931", "name": "Pisarevka", "toponymName": "Pisarevka", "lat": "53.6556", "fclName": "city, village,...", "geonameId": 8279919, "fcode": "PPL", "population": 0, "countryCode": "BY", "countryId": "630336"}, {"fcl": "P", "countryName": "Russia", "adminCode1": "08", "fcodeName": "populated place", "adminName1": "Bashkortostan", "lng": "55.20454", "name": "Pisarevka", "toponymName": "Pisarevka", "lat": "53.76872", "fclName": "city, village,...", "geonameId": 509351, "fcode": "PPL", "population": 0, "countryCode": "RU", "countryId": "2017370"}, {"fcl": "P", "countryName": "Russia", "adminCode1": "10", "fcodeName": "populated place", "adminName1": "Brjansk", "lng": "31.8436", "name": "Pisar\u00ebvka", "toponymName": "Pisar\u00ebvka", "lat": "52.761", "fclName": "city, village,...", "geonameId": 509354, "fcode": "PPL", "population": 0, "countryCode": "RU", "countryId": "2017370"}, {"fcl": "P", "countryName": "Ukraine", "adminCode1": "07", "fcodeName": "populated place", "adminName1": "Kharkiv", "lng": "35.75693", "name": "Pisarevka", "toponymName": "Pysarivka", "lat": "50.24704", "fclName": "city, village,...", "geonameId": 697168, "fcode": "PPL", "population": 0, "countryCode": "UA", "countryId": "690791"}, {"fcl": "P", "countryName": "Ukraine", "adminCode1": "11", "fcodeName": "populated place", "adminName1": "Crimea", "lng": "33.21438", "name": "Pisarevka", "toponymName": "Pisarevka", "lat": "45.62837", "fclName": "city, village,...", "geonameId": 697178, "fcode": "PPL", "population": 0, "countryCode": "UA", "countryId": "690791"}, {"fcl": "P", "countryName": "Ukraine", "adminCode1": "21", "fcodeName": "populated place", "adminName1": "Sumy", "lng": "33.83213", "name": "Pyharivka", "toponymName": "Pyharivka", "lat": "52.14174", "fclName": "city, village,...", "geonameId": 697246, "fcode": "PPL", "population": 0, "countryCode": "UA", "countryId": "690791"}, {"fcl": "P", "countryName": "Ukraine", "adminCode1": "09", "fcodeName": "populated place", "adminName1": "Khmelnytskyi", "lng": "27.3305", "name": "Pisarevka", "toponymName": "Pisarevka", "lat": "49.83542", "fclName": "city, village,...", "geonameId": 697169, "fcode": "PPL", "population": 0, "countryCode": "UA", "countryId": "690791"}, {"fcl": "P", "countryName": "Ukraine", "adminCode1": "09", "fcodeName": "populated place", "adminName1": "Khmelnytskyi", "lng": "26.755", "name": "Pisarevka", "toponymName": "Pisarevka", "lat": "49.6193", "fclName": "city, village,...", "geonameId": 697170, "fcode": "PPL", "population": 0, "countryCode": "UA", "countryId": "690791"}, {"fcl": "P", "countryName": "Ukraine", "adminCode1": "09", "fcodeName": "populated place", "adminName1": "Khmelnytskyi", "lng": "26.44649", "name": "Pisarevka", "toponymName": "Pisarevka", "lat": "49.52052", "fclName": "city, village,...", "geonameId": 697171, "fcode": "PPL", "population": 0, "countryCode": "UA", "countryId": "690791"}, {"fcl": "P", "countryName": "Ukraine", "adminCode1": "23", "fcodeName": "populated place", "adminName1": "Vinnyts'ka", "lng": "28.60449", "name": "Pisarevka", "toponymName": "Pisarevka", "lat": "49.1887", "fclName": "city, village,...", "geonameId": 697173, "fcode": "PPL", "population": 0, "countryCode": "UA", "countryId": "690791"}, {"fcl": "P", "countryName": "Ukraine", "adminCode1": "04", "fcodeName": "populated place", "adminName1": "Dnipropetrovsk", "lng": "35.77722", "name": "Pisarevka", "toponymName": "Pisarevka", "lat": "48.34374", "fclName": "city, village,...", "geonameId": 697175, "fcode": "PPL", "population": 0, "countryCode": "UA", "countryId": "690791"}, {"fcl": "P", "countryName": "Ukraine", "adminCode1": "17", "fcodeName": "populated place", "adminName1": "Odessa", "lng": "29.04783", "name": "Pisarevka", "toponymName": "Pisarevka", "lat": "48.05489", "fclName": "city, village,...", "geonameId": 697177, "fcode": "PPL", "population": 0, "countryCode": "UA", "countryId": "690791"}, {"fcl": "P", "countryName": "Russia", "adminCode1": "86", "fcodeName": "populated place", "adminName1": "Voronezj", "lng": "40.88583", "name": "Pisarevka", "toponymName": "Pisarevka", "lat": "50.83556", "fclName": "city, village,...", "geonameId": 807879, "fcode": "PPL", "population": 0, "countryCode": "RU", "countryId": "2017370"}, {"fcl": "P", "countryName": "Russia", "adminCode1": "86", "fcodeName": "populated place", "adminName1": "Voronezj", "lng": "40.67472", "name": "Pisarevka", "toponymName": "Pisarevka", "lat": "51.86611", "fclName": "city, village,...", "geonameId": 808654, "fcode": "PPL", "population": 0, "countryCode": "RU", "countryId": "2017370"}, {"fcl": "P", "countryName": "Ukraine", "adminCode1": "07", "fcodeName": "populated place", "adminName1": "Kharkiv", "lng": "37.63583", "name": "Pisarevka", "toponymName": "Pisarevka", "lat": "50.14333", "fclName": "city, village,...", "geonameId": 806964, "fcode": "PPL", "population": 0, "countryCode": "UA", "countryId": "690791"}, {"fcl": "P", "countryName": "Ukraine", "adminCode1": "21", "fcodeName": "populated place", "adminName1": "Sumy", "lng": "35.47989", "name": "Velyka Pysarivka", "toponymName": "Velyka Pysarivka", "lat": "50.4243", "fclName": "city, village,...", "geonameId": 690230, "fcode": "PPL", "population": 5235, "countryCode": "UA", "countryId": "690791"}, {"fcl": "P", "countryName": "Russia", "adminCode1": "76", "fcodeName": "populated place", "adminName1": "Tula", "lng": "38.41932", "name": "Pisarevo", "toponymName": "Pisarevo", "lat": "53.83736", "fclName": "city, village,...", "geonameId": 509346, "fcode": "PPL", "population": 0, "countryCode": "RU", "countryId": "2017370"}, {"fcl": "P", "countryName": "Russia", "adminCode1": "76", "fcodeName": "populated place", "adminName1": "Tula", "lng": "38.81536", "name": "Pisarevo", "toponymName": "Pisarevo", "lat": "53.85047", "fclName": "city, village,...", "geonameId": 509350, "fcode": "PPL", "population": 0, "countryCode": "RU", "countryId": "2017370"}, {"fcl": "P", "countryName": "Ukraine", "adminCode1": "27", "fcodeName": "populated place", "adminName1": "Zhytomyr", "lng": "29.00623", "name": "Pysarivka", "toponymName": "Pysarivka", "lat": "50.94514", "fclName": "city, village,...", "geonameId": 697167, "fcode": "PPL", "population": 0, "countryCode": "UA", "countryId": "690791"}, {"fcl": "P", "countryName": "Russia", "adminCode1": "43", "fcodeName": "populated place", "adminName1": "Lipetsk", "lng": "38.8574", "name": "Aleksandrovka", "toponymName": "Aleksandrovka", "lat": "52.5355", "fclName": "city, village,...", "geonameId": 583257, "fcode": "PPL", "population": 0, "countryCode": "RU", "countryId": "2017370"}, {"fcl": "P", "countryName": "Ukraine", "adminCode1": "27", "fcodeName": "populated place", "adminName1": "Zhytomyr", "lng": "28.37249", "name": "Pysarivka", "toponymName": "Pysarivka", "lat": "50.68178", "fclName": "city, village,...", "geonameId": 8465654, "fcode": "PPL", "population": 0, "countryCode": "UA", "countryId": "690791"}, {"fcl": "P", "countryName": "Belarus", "adminCode1": "06", "fcodeName": "populated place", "adminName1": "Mogilev", "lng": "30.0212", "name": "Pisar\u00ebvka Glukhskaya", "toponymName": "Pisar\u00ebvka Glukhskaya", "lat": "53.6505", "fclName": "city, village,...", "geonameId": 8540550, "fcode": "PPL", "population": 0, "countryCode": "BY", "countryId": "630336"}, {"fcl": "P", "countryName": "Russia", "adminCode1": "75", "fcodeName": "populated place", "adminName1": "Tomsk", "lng": "85.01482", "name": "Pisarevo", "toponymName": "Pisarevo", "lat": "56.39474", "fclName": "city, village,...", "geonameId": 1494939, "fcode": "PPL", "population": 0, "countryCode": "RU", "countryId": "2017370"}, {"fcl": "P", "countryName": "Ukraine", "adminCode1": "07", "fcodeName": "populated place", "adminName1": "Kharkiv", "lng": "36.84536", "name": "Verkhnya Pysarivka", "toponymName": "Verkhnya Pysarivka", "lat": "50.18643", "fclName": "city, village,...", "geonameId": 806663, "fcode": "PPL", "population": 0, "countryCode": "UA", "countryId": "690791"}, {"fcl": "P", "countryName": "Russia", "adminCode1": "56", "fcodeName": "populated place", "adminName1": "Orjol", "lng": "36.66241", "name": "Pisarevo", "toponymName": "Pisarevo", "lat": "52.40949", "fclName": "city, village,...", "geonameId": 509355, "fcode": "PPL", "population": 0, "countryCode": "RU", "countryId": "2017370"}, {"fcl": "P", "countryName": "Russia", "adminCode1": "72", "fcodeName": "populated place", "adminName1": "Tambov", "lng": "40.92972", "name": "Petrovka", "toponymName": "Petrovka", "lat": "52.22889", "fclName": "city, village,...", "geonameId": 510099, "fcode": "PPL", "population": 0, "countryCode": "RU", "countryId": "2017370"}, {"fcl": "P", "countryName": "Ukraine", "adminCode1": "02", "fcodeName": "populated place", "adminName1": "Chernihiv", "lng": "32.7835", "name": "Lebedyn", "toponymName": "Lebedyn", "lat": "51.51848", "fclName": "city, village,...", "geonameId": 697165, "fcode": "PPL", "population": 0, "countryCode": "UA", "countryId": "690791"}, {"fcl": "P", "countryName": "Ukraine", "adminCode1": "21", "fcodeName": "populated place", "adminName1": "Sumy", "lng": "34.79999", "name": "Pysarivka", "toponymName": "Pysarivka", "lat": "51.07398", "fclName": "city, village,...", "geonameId": 697166, "fcode": "PPL", "population": 0, "countryCode": "UA", "countryId": "690791"}, {"fcl": "P", "countryName": "Ukraine", "adminCode1": "23", "fcodeName": "populated place", "adminName1": "Vinnyts'ka", "lng": "28.12808", "name": "Pysarivka", "toponymName": "Pysarivka", "lat": "48.67343", "fclName": "city, village,...", "geonameId": 697174, "fcode": "PPL", "population": 0, "countryCode": "UA", "countryId": "690791"}, {"fcl": "P", "countryName": "Ukraine", "adminCode1": "23", "fcodeName": "populated place", "adminName1": "Vinnyts'ka", "lng": "28.39798", "name": "Pysarivka", "toponymName": "Pysarivka", "lat": "48.32655", "fclName": "city, village,...", "geonameId": 697176, "fcode": "PPL", "population": 0, "countryCode": "UA", "countryId": "690791"}], "totalResultsCount": 47, "url": "http://api.geonames.org/search?north=78.0&west=24.8&south=38.6&name=%D0%9F%D0%B8%D1%81%D0%B0%D1%80%D0%B5%D0%B2%D0%BA%D0%B0&username=jaguillette&east=180&featureClass=P&type=json"}