{"totalResultsCount":2,"geonames":[{"adminCode1":"10","lng":"32.31206","geonameId":516874,"toponymName":"Novyy Ropsk","countryId":"2017370","fcl":"P","population":0,"countryCode":"RU","name":"Novyy Ropsk","fclName":"city, village,...","countryName":"Russia","fcodeName":"populated place","adminName1":"Brjansk","lat":"52.29781","fcode":"PPL"},{"adminCode1":"10","lng":"32.25882","geonameId":487912,"toponymName":"Staryy Ropsk","countryId":"2017370","fcl":"P","population":0,"countryCode":"RU","name":"Staryy Ropsk","fclName":"city, village,...","countryName":"Russia","fcodeName":"populated place","adminName1":"Brjansk","lat":"52.30876","fcode":"PPL"}]}